yihan_helper/__init__.py
yihan_helper/yihan1.py
yihan_helper-0.1.dist-info/METADATA
yihan_helper-0.1.dist-info/WHEEL
yihan_helper-0.1.dist-info/top_level.txt
yihan_helper-0.1.dist-info/RECORD
