Metadata-Version: 2.1
Name: yihan-helper
Version: 0.1
Summary: Yihan Helper base code
Home-page: https://git.un.org/gsd/unite.un.org.ml.unisdr.ds.git
Author: Yihan Bao
Author-email: yihan.bap@un.org
License: MIT
Platform: UNKNOWN
